setup.py
diaspy/__init__.py
diaspy/client.py
diaspy/connection.py
diaspy/conversations.py
diaspy/errors.py
diaspy/models.py
diaspy/notifications.py
diaspy/people.py
diaspy/search.py
diaspy/streams.py
diaspy.egg-info/PKG-INFO
diaspy.egg-info/SOURCES.txt
diaspy.egg-info/dependency_links.txt
diaspy.egg-info/requires.txt
diaspy.egg-info/top_level.txt