Metadata-Version: 1.0
Name: diaspy
Version: 0.3.0
Summary: A Python API to the social network Diaspora*
Home-page: https://github.com/Javafant/diaspora-api
Author: Moritz Kiefer
Author-email: moritz.kiefer@gmail.com
License: UNKNOWN
Platform: UNKNOWN
